odoo/addons/l10n_es_vat_book_invoice_summary/README.rst
odoo/addons/l10n_es_vat_book_invoice_summary/__init__.py
odoo/addons/l10n_es_vat_book_invoice_summary/__manifest__.py
odoo/addons/l10n_es_vat_book_invoice_summary/i18n/es.po
odoo/addons/l10n_es_vat_book_invoice_summary/i18n/l10n_es_vat_book_invoice_summary.pot
odoo/addons/l10n_es_vat_book_invoice_summary/readme/CONTRIBUTORS.md
odoo/addons/l10n_es_vat_book_invoice_summary/readme/DESCRIPTION.md
odoo/addons/l10n_es_vat_book_invoice_summary/report/__init__.py
odoo/addons/l10n_es_vat_book_invoice_summary/report/vat_book_xlsx.py
odoo/addons/l10n_es_vat_book_invoice_summary/static/description/icon.png
odoo/addons/l10n_es_vat_book_invoice_summary/static/description/index.html
odoo/addons/l10n_es_vat_book_invoice_summary/tests/__init__.py
odoo/addons/l10n_es_vat_book_invoice_summary/tests/test_l10n_es_vat_book_invoice_summary.py
odoo_addon_l10n_es_vat_book_invoice_summary-17.0.1.0.0.2.dist-info/METADATA
odoo_addon_l10n_es_vat_book_invoice_summary-17.0.1.0.0.2.dist-info/WHEEL
odoo_addon_l10n_es_vat_book_invoice_summary-17.0.1.0.0.2.dist-info/top_level.txt
odoo_addon_l10n_es_vat_book_invoice_summary-17.0.1.0.0.2.dist-info/RECORD
